langchain_perplexity/__init__.py
langchain_perplexity/chat_models.py
langchain_perplexity/py.typed
langchain_perplexity-1.0.0.dist-info/METADATA
langchain_perplexity-1.0.0.dist-info/WHEEL
langchain_perplexity-1.0.0.dist-info/licenses/LICENSE
langchain_perplexity-1.0.0.dist-info/RECORD
