Metadata-Version: 2.4
Name: langchain-perplexity
Version: 1.0.0
Summary: An integration package connecting Perplexity and LangChain
Project-URL: homepage, https://docs.langchain.com/oss/python/integrations/providers/perplexity
Project-URL: repository, https://github.com/langchain-ai/langchain/tree/master/libs/partners/perplexity
Project-URL: changelog, https://github.com/langchain-ai/langchain/releases?q=%22langchain-perplexity%22
Project-URL: docs, https://reference.langchain.com/python/integrations/langchain_perplexity/
Project-URL: twitter, https://x.com/LangChainAI
Project-URL: slack, https://www.langchain.com/join-community
Project-URL: reddit, https://www.reddit.com/r/LangChain/
License: MIT
License-File: LICENSE
Requires-Python: <4.0.0,>=3.10.0
Requires-Dist: langchain-core<2.0.0,>=1.0.0
Requires-Dist: openai<3.0.0,>=2.0.0
